README
setup.py
Zone.egg-info/PKG-INFO
Zone.egg-info/SOURCES.txt
Zone.egg-info/dependency_links.txt
Zone.egg-info/not-zip-safe
Zone.egg-info/requires.txt
Zone.egg-info/top_level.txt
zone/__init__.py