Metadata-Version: 1.0
Name: Zone
Version: 0.0.0dev
Summary: Asynchronous RPC framework based on Apache Avro and Trollius
Home-page: UNKNOWN
Author: abing
Author-email: UNKNOWN
License: PRIVATE
Platform: UNKNOWN
